Workbook

Sheet Sheet1
A1: Product | B1: (All)
B3: Column Labels
B4: Electronics | F4: Furniture | J4: Total Sum of Revenue | K4: Total Sum of Profit | L4: Total Sum of Profit_Margin_Pct | M4: Total Sum of avg_order_value
A5: Row Labels | B5: Sum of Revenue | C5: Sum of Profit | D5: Sum of Profit_Margin_Pct | E5: Sum of avg_order_value | F5: Sum of Revenue | G5: Sum of Profit | H5: Sum of Profit_Margin_Pct | I5: Sum of avg_order_value
A6: Brisbane | B6: 0.51827467 | C6: 1550 | D6: 33.659066 | E6: 657.85714 | F6: 0.10230438 | G6: 288 | H6: 31.683168 | I6: 227.25 | J6: 0.62057905 | K6: 1838 | L6: 33.333333 | M6: 501.27273
A7: Melbourne | B7: 0.17163276 | C7: 521 | D7: 34.163934 | E7: 152.5 | F7: 0 | H7: #DIV/0! | I7: #DIV/0! | J7: 0.17163276 | K7: 521 | L7: 34.163934 | M7: 152.5
A8: Perth | B8: 0.026729692 | C8: 95 | D8: 40 | E8: 23.75 | F8: 0.045018429 | G8: 120 | H8: 30 | I8: 400 | J8: 0.071748122 | K8: 215 | L8: 33.72549 | M8: 57.954545
A9: Sydney | B9: 0.091021637 | C9: 287.5 | D9: 35.548686 | E9: 89.861111 | F9: 0.045018429 | G9: 160 | H9: 40 | I9: 200 | J9: 0.13604007 | K9: 447.5 | L9: 37.021717 | M9: 109.88636
A10: Grand Total | B10: 0.80765876 | C10: 2453.5 | D10: 34.189166 | E10: 199.34028 | F10: 0.19234124 | G10: 568 | H10: 33.23581 | I10: 244.14286 | J10: 1 | K10: 3021.5 | L10: 34.005796 | M10: 206.63372

Sheet Sales_Data
O1: BrisBane Total | P1: Brisbane High Value Count | Q1: AVG Electronics Revenue
O2: =SUMIFS(Table1[Revenue],Table1[Region],"Brisbane") -> 5514 | P2: =COUNTIFS(Table1[[#All],[Region]],"Brisbane",Table1[[#All],[Flag high]],"Yes") -> 3 | Q2: =AVERAGEIFS(Table1[[#All],[Revenue]],Table1[[#All],[Category]],"Electronics") -> 652.38636
D3: electronics= | E3: =SUMIFS(Table1[Revenue],Table1[Category],"Electronics") -> 7176.25 | G3: total = | H3: =SUM(Table1[Revenue]) -> 8885.25 | I3: avg_elec | J3: =AVERAGEIFS(Table1[Discount],Table1[Category],"Electronics") *100 -> 6.8181818 | Q3: Region | R3: total revenue
D4: furniture = | E4: =SUMIFS(Table1[Revenue],Table1[Category],"Furniture") -> 1709 | G4: electronics% = | H4: =(E3/H3)*100 -> 80.765876 | I4: avg_fur | J4: =AVERAGEIFS(Table1[Discount],Table1[Category],"Furniture") *100 -> 16.25 | O4: =MAX(Table1[Order_Description]) -> 0 | Q4: Brisbane | R4: =SUMIFS(Table1[Revenue],Table1[Region],Q4) -> 5514
G5: fur% | H5: =(E4/H3)*100 -> 19.234124 | O5: =INDEX(Table1[Product],MATCH(MAX(Table1[Order_Description]),O4,0)) -> Laptop | Q5: Sydney | R5: =SUMIFS(Table1[Revenue],Table1[Region],Q5) -> 1208.75
Q6: Melbourne | R6: =SUMIFS(Table1[Revenue],Table1[Region],Q6) -> 1525
Q7: Perth | R7: =SUMIFS(Table1[Revenue],Table1[Region],Q7) -> 637.5
A10: Order_ID | B10: Date | C10: Customer_Name | D10: Product | E10: Category | F10: Region | G10: Quantity | H10: Unit_Price | I10: Discount | J10: Revenue | K10: Cost_Price | L10: Flag high | M10: Profit | N10: Month | O10: Day_of_Week | P10: Order_Description | Q10: Profit_margin
A11: 1001 | B11: 45306 | C11: Alice Johnson | D11: Laptop | E11: Electronics | F11: Brisbane | G11: 2 | H11: 1200 | I11: 0.1 | J11: =Table1[[#This Row],[Quantity]] * Table1[[#This Row],[Unit_Price]] * (1 - Table1[[#This Row],[Discount]] ) -> 2160 | K11: =IFERROR(VLOOKUP(Table1[[#This Row],[Product]],Product_Lookup!A:B,2,FALSE), "Not Found") -> 800 | L11: =IF(Table1[[#This Row],[Revenue]]>1000,"yes","no") -> yes | M11: =(Table1[[#This Row],[Unit_Price]]-Table1[[#This Row],[Cost_Price]]) *Table1[[#This Row],[Quantity]] *( 1 -Table1[[#This Row],[Discount]] ) -> 720 | N11: =TEXT(Table1[[#This Row],[Date]],"mmmm") -> January | O11: =TEXT(Table1[[#This Row],[Date]],"dddd") -> Monday | P11: =C11 & "ordered " &Table1[[#This Row],[Quantity]] & " " & Table1[[#This Row],[Product]] -> Alice Johnsonordered 2 Laptop | Q11: =(Table1[[#This Row],[Profit]]/Table1[[#This Row],[Revenue]])*100 -> 33.333333
A12: 1002 | B12: 45307 | C12: Bob Smith | D12: Mouse | E12: Electronics | F12: Sydney | G12: 5 | H12: 25 | I12: 0.05 | J12: =Table1[[#This Row],[Quantity]] * Table1[[#This Row],[Unit_Price]] * (1 - Table1[[#This Row],[Discount]] ) -> 118.75 | K12: =IFERROR(VLOOKUP(Table1[[#This Row],[Product]],Product_Lookup!A:B,2,FALSE), "Not Found") -> 15 | L12: =IF(Table1[[#This Row],[Revenue]]>1000,"yes","no") -> no | M12: =(Table1[[#This Row],[Unit_Price]]-Table1[[#This Row],[Cost_Price]]) *Table1[[#This Row],[Quantity]] *( 1 -Table1[[#This Row],[Discount]] ) -> 47.5 | N12: =TEXT(Table1[[#This Row],[Date]],"mmmm") -> January | O12: =TEXT(Table1[[#This Row],[Date]],"dddd") -> Tuesday | P12: =C12 & "ordered " &Table1[[#This Row],[Quantity]] & " " & Table1[[#This Row],[Product]] -> Bob Smithordered 5 Mouse | Q12: =(Table1[[#This Row],[Profit]]/Table1[[#This Row],[Revenue]])*100 -> 40
A13: 1003 | B13: 45308 | C13: Charlie Brown | D13: Keyboard | E13: Electronics | F13: Brisbane | G13: 3 | H13: 75 | I13: 0 | J13: =Table1[[#This Row],[Quantity]] * Table1[[#This Row],[Unit_Price]] * (1 - Table1[[#This Row],[Discount]] ) -> 225 | K13: =IFERROR(VLOOKUP(Table1[[#This Row],[Product]],Product_Lookup!A:B,2,FALSE), "Not Found") -> 45 | L13: =IF(Table1[[#This Row],[Revenue]]>1000,"yes","no") -> no | M13: =(Table1[[#This Row],[Unit_Price]]-Table1[[#This Row],[Cost_Price]]) *Table1[[#This Row],[Quantity]] *( 1 -Table1[[#This Row],[Discount]] ) -> 90 | N13: =TEXT(Table1[[#This Row],[Date]],"mmmm") -> January | O13: =TEXT(Table1[[#This Row],[Date]],"dddd") -> Wednesday | P13: =C13 & "ordered " &Table1[[#This Row],[Quantity]] & " " & Table1[[#This Row],[Product]] -> Charlie Brownordered 3 Keyboard | Q13: =(Table1[[#This Row],[Profit]]/Table1[[#This Row],[Revenue]])*100 -> 40
A14: 1004 | B14: 45309 | C14: David Wilson | D14: Monitor | E14: Electronics | F14: Melbourne | G14: 1 | H14: 300 | I14: 0.15 | J14: =Table1[[#This Row],[Quantity]] * Table1[[#This Row],[Unit_Price]] * (1 - Table1[[#This Row],[Discount]] ) -> 255 | K14: =IFERROR(VLOOKUP(Table1[[#This Row],[Product]],Product_Lookup!A:B,2,FALSE), "Not Found") -> 200 | L14: =IF(Table1[[#This Row],[Revenue]]>1000,"yes","no") -> no | M14: =(Table1[[#This Row],[Unit_Price]]-Table1[[#This Row],[Cost_Price]]) *Table1[[#This Row],[Quantity]] *( 1 -Table1[[#This Row],[Discount]] ) -> 85 | N14: =TEXT(Table1[[#This Row],[Date]],"mmmm") -> January | O14: =TEXT(Table1[[#This Row],[Date]],"dddd") -> Thursday | P14: =C14 & "ordered " &Table1[[#This Row],[Quantity]] & " " & Table1[[#This Row],[Product]] -> David Wilsonordered 1 Monitor | Q14: =(Table1[[#This Row],[Profit]]/Table1[[#This Row],[Revenue]])*100 -> 33.333333
A15: 1005 | B15: 45310 | C15: Eve Davis | D15: Laptop | E15: Electronics | F15: Brisbane | G15: 1 | H15: 1200 | I15: 0.1 | J15: =Table1[[#This Row],[Quantity]] * Table1[[#This Row],[Unit_Price]] * (1 - Table1[[#This Row],[Discount]] ) -> 1080 | K15: =IFERROR(VLOOKUP(Table1[[#This Row],[Product]],Product_Lookup!A:B,2,FALSE), "Not Found") -> 800 | L15: =IF(Table1[[#This Row],[Revenue]]>1000,"yes","no") -> yes | M15: =(Table1[[#This Row],[Unit_Price]]-Table1[[#This Row],[Cost_Price]]) *Table1[[#This Row],[Quantity]] *( 1 -Table1[[#This Row],[Discount]] ) -> 360 | N15: =TEXT(Table1[[#This Row],[Date]],"mmmm") -> January | O15: =TEXT(Table1[[#This Row],[Date]],"dddd") -> Friday | P15: =C15 & "ordered " &Table1[[#This Row],[Quantity]] & " " & Table1[[#This Row],[Product]] -> Eve Davisordered 1 Laptop | Q15: =(Table1[[#This Row],[Profit]]/Table1[[#This Row],[Revenue]])*100 -> 33.333333
A16: 1006 | B16: 45311 | C16: Frank Miller | D16: Desk Chair | E16: Furniture | F16: Sydney | G16: 2 | H16: 250 | I16: 0.2 | J16: =Table1[[#This Row],[Quantity]] * Table1[[#This Row],[Unit_Price]] * (1 - Table1[[#This Row],[Discount]] ) -> 400 | K16: =IFERROR(VLOOKUP(Table1[[#This Row],[Product]],Product_Lookup!A:B,2,FALSE), "Not Found") -> 150 | L16: =IF(Table1[[#This Row],[Revenue]]>1000,"yes","no") -> no | M16: =(Table1[[#This Row],[Unit_Price]]-Table1[[#This Row],[Cost_Price]]) *Table1[[#This Row],[Quantity]] *( 1 -Table1[[#This Row],[Discount]] ) -> 160 | N16: =TEXT(Table1[[#This Row],[Date]],"mmmm") -> January | O16: =TEXT(Table1[[#This Row],[Date]],"dddd") -> Saturday | P16: =C16 & "ordered " &Table1[[#This Row],[Quantity]] & " " & Table1[[#This Row],[Product]] -> Frank Millerordered 2 Desk Chair | Q16: =(Table1[[#This Row],[Profit]]/Table1[[#This Row],[Revenue]])*100 -> 40
A17: 1007 | B17: 45312 | C17: Grace Moore | D17: Standing Desk | E17: Furniture | F17: Brisbane | G17: 1 | H17: 500 | I17: 0.1 | J17: =Table1[[#This Row],[Quantity]] * Table1[[#This Row],[Unit_Price]] * (1 - Table1[[#This Row],[Discount]] ) -> 450 | K17: =IFERROR(VLOOKUP(Table1[[#This Row],[Product]],Product_Lookup!A:B,2,FALSE), "Not Found") -> 350 | L17: =IF(Table1[[#This Row],[Revenue]]>1000,"yes","no") -> no | M17: =(Table1[[#This Row],[Unit_Price]]-Table1[[#This Row],[Cost_Price]]) *Table1[[#This Row],[Quantity]] *( 1 -Table1[[#This Row],[Discount]] ) -> 135 | N17: =TEXT(Table1[[#This Row],[Date]],"mmmm") -> January | O17: =TEXT(Table1[[#This Row],[Date]],"dddd") -> Sunday | P17: =C17 & "ordered " &Table1[[#This Row],[Quantity]] & " " & Table1[[#This Row],[Product]] -> Grace Mooreordered 1 Standing Desk | Q17: =(Table1[[#This Row],[Profit]]/Table1[[#This Row],[Revenue]])*100 -> 30
A18: 1008 | B18: 45313 | C18: Henry Taylor | D18: Mouse | E18: Electronics | F18: Perth | G18: 10 | H18: 25 | I18: 0.05 | J18: =Table1[[#This Row],[Quantity]] * Table1[[#This Row],[Unit_Price]] * (1 - Table1[[#This Row],[Discount]] ) -> 237.5 | K18: =IFERROR(VLOOKUP(Table1[[#This Row],[Product]],Product_Lookup!A:B,2,FALSE), "Not Found") -> 15 | L18: =IF(Table1[[#This Row],[Revenue]]>1000,"yes","no") -> no | M18: =(Table1[[#This Row],[Unit_Price]]-Table1[[#This Row],[Cost_Price]]) *Table1[[#This Row],[Quantity]] *( 1 -Table1[[#This Row],[Discount]] ) -> 95 | N18: =TEXT(Table1[[#This Row],[Date]],"mmmm") -> January | O18: =TEXT(Table1[[#This Row],[Date]],"dddd") -> Monday | P18: =C18 & "ordered " &Table1[[#This Row],[Quantity]] & " " & Table1[[#This Row],[Product]] -> Henry Taylorordered 10 Mouse | Q18: =(Table1[[#This Row],[Profit]]/Table1[[#This Row],[Revenue]])*100 -> 40
A19: 1009 | B19: 45314 | C19: Ivy Wilson | D19: Keyboard | E19: Electronics | F19: Sydney | G19: 2 | H19: 75 | I19: 0 | J19: =Table1[[#This Row],[Quantity]] * Table1[[#This Row],[Unit_Price]] * (1 - Table1[[#This Row],[Discount]] ) -> 150 | K19: =IFERROR(VLOOKUP(Table1[[#This Row],[Product]],Product_Lookup!A:B,2,FALSE), "Not Found") -> 45 | L19: =IF(Table1[[#This Row],[Revenue]]>1000,"yes","no") -> no | M19: =(Table1[[#This Row],[Unit_Price]]-Table1[[#This Row],[Cost_Price]]) *Table1[[#This Row],[Quantity]] *( 1 -Table1[[#This Row],[Discount]] ) -> 60 | N19: =TEXT(Table1[[#This Row],[Date]],"mmmm") -> January | O19: =TEXT(Table1[[#This Row],[Date]],"dddd") -> Tuesday | P19: =C19 & "ordered " &Table1[[#This Row],[Quantity]] & " " & Table1[[#This Row],[Product]] -> Ivy Wilsonordered 2 Keyboard | Q19: =(Table1[[#This Row],[Profit]]/Table1[[#This Row],[Revenue]])*100 -> 40
A20: 1010 | B20: 45315 | C20: Jack Brown | D20: Laptop | E20: Electronics | F20: Melbourne | G20: 1 | H20: 1200 | I20: 0.1 | J20: =Table1[[#This Row],[Quantity]] * Table1[[#This Row],[Unit_Price]] * (1 - Table1[[#This Row],[Discount]] ) -> 1080 | K20: =IFERROR(VLOOKUP(Table1[[#This Row],[Product]],Product_Lookup!A:B,2,FALSE), "Not Found") -> 800 | L20: =IF(Table1[[#This Row],[Revenue]]>1000,"yes","no") -> yes | M20: =(Table1[[#This Row],[Unit_Price]]-Table1[[#This Row],[Cost_Price]]) *Table1[[#This Row],[Quantity]] *( 1 -Table1[[#This Row],[Discount]] ) -> 360 | N20: =TEXT(Table1[[#This Row],[Date]],"mmmm") -> January | O20: =TEXT(Table1[[#This Row],[Date]],"dddd") -> Wednesday | P20: =C20 & "ordered " &Table1[[#This Row],[Quantity]] & " " & Table1[[#This Row],[Product]] -> Jack Brownordered 1 Laptop | Q20: =(Table1[[#This Row],[Profit]]/Table1[[#This Row],[Revenue]])*100 -> 33.333333
A21: 1011 | B21: 45316 | C21: Kelly Davis | D21: Office Chair | E21: Furniture | F21: Brisbane | G21: 3 | H21: 180 | I21: 0.15 | J21: =Table1[[#This Row],[Quantity]] * Table1[[#This Row],[Unit_Price]] * (1 - Table1[[#This Row],[Discount]] ) -> 459 | K21: =IFERROR(VLOOKUP(Table1[[#This Row],[Product]],Product_Lookup!A:B,2,FALSE), "Not Found") -> 120 | L21: =IF(Table1[[#This Row],[Revenue]]>1000,"yes","no") -> no | M21: =(Table1[[#This Row],[Unit_Price]]-Table1[[#This Row],[Cost_Price]]) *Table1[[#This Row],[Quantity]] *( 1 -Table1[[#This Row],[Discount]] ) -> 153 | N21: =TEXT(Table1[[#This Row],[Date]],"mmmm") -> January | O21: =TEXT(Table1[[#This Row],[Date]],"dddd") -> Thursday | P21: =C21 & "ordered " &Table1[[#This Row],[Quantity]] & " " & Table1[[#This Row],[Product]] -> Kelly Davisordered 3 Office Chair | Q21: =(Table1[[#This Row],[Profit]]/Table1[[#This Row],[Revenue]])*100 -> 33.333333
A22: 1012 | B22: 45317 | C22: Liam Smith | D22: Monitor | E22: Electronics | F22: Sydney | G22: 2 | H22: 300 | I22: 0.1 | J22: =Table1[[#This Row],[Quantity]] * Table1[[#This Row],[Unit_Price]] * (1 - Table1[[#This Row],[Discount]] ) -> 540 | K22: =IFERROR(VLOOKUP(Table1[[#This Row],[Product]],Product_Lookup!A:B,2,FALSE), "Not Found") -> 200 | L22: =IF(Table1[[#This Row],[Revenue]]>1000,"yes","no") -> no | M22: =(Table1[[#This Row],[Unit_Price]]-Table1[[#This Row],[Cost_Price]]) *Table1[[#This Row],[Quantity]] *( 1 -Table1[[#This Row],[Discount]] ) -> 180 | N22: =TEXT(Table1[[#This Row],[Date]],"mmmm") -> January | O22: =TEXT(Table1[[#This Row],[Date]],"dddd") -> Friday | P22: =C22 & "ordered " &Table1[[#This Row],[Quantity]] & " " & Table1[[#This Row],[Product]] -> Liam Smithordered 2 Monitor | Q22: =(Table1[[#This Row],[Profit]]/Table1[[#This Row],[Revenue]])*100 -> 33.333333
... A25: 1015 | B25: 45320 | C25: Olivia Brown | D25: Mouse | E25: Electronics | F25: Melbourne | G25: 8 | H25: 25 | I25: 0.05 | J25: =Table1[[#This Row],[Quantity]] * Table1[[#This Row],[Unit_Price]] * (1 - Table1[[#This Row],[Discount]] ) -> 190 | K25: =IFERROR(VLOOKUP(Table1[[#This Row],[Product]],Product_Lookup!A:B,2,FALSE), "Not Found") -> 15 | L25: =IF(Table1[[#This Row],[Revenue]]>1000,"yes","no") -> no | M25: =(Table1[[#This Row],[Unit_Price]]-Table1[[#This Row],[Cost_Price]]) *Table1[[#This Row],[Quantity]] *( 1 -Table1[[#This Row],[Discount]] ) -> 76 | N25: =TEXT(Table1[[#This Row],[Date]],"mmmm") -> January | O25: =TEXT(Table1[[#This Row],[Date]],"dddd") -> Monday | P25: =C25 & "ordered " &Table1[[#This Row],[Quantity]] & " " & Table1[[#This Row],[Product]] -> Olivia Brownordered 8 Mouse | Q25: =(Table1[[#This Row],[Profit]]/Table1[[#This Row],[Revenue]])*100 -> 40
J28: =COUNTIFS(Table1[Day_of_Week],"Monday") -> 3
E29: =MATCH(MAX(Table1[Revenue]),Table1[Revenue],0) -> 1 | J29: =COUNTIFS(Table1[Day_of_Week],"Tuesday") -> 2 | M29: helper_column | N29: product | P29: =SUMIFS(Table1[Revenue],Table1[Region],"Sydney",Table1[Category],"Electronics") -> 808.75
E30: =INDEX(Table1[Region],2) -> Sydney | J30: =COUNTIFS(Table1[Day_of_Week],"Monday") -> 3 | M30: =SUMIFS(Table1[Revenue],Table1[Product],"Laptop") -> 5460 | N30: Laptop | P30: =AVERAGEIFS(Table1[Revenue],Table1[Region],"Brisbane") -> 919
E31: =INDEX(Table1[Region],MATCH(MAX(Table1[Revenue]),Table1[Revenue],0)) -> Brisbane | J31: =COUNTIFS(Table1[Day_of_Week],"Monday") -> 3 | M31: =SUMIFS(Table1[Revenue],Table1[Product],"Mouse") -> 546.25 | N31: Mouse | P31: =SUMIFS(Table1[Quantity],Table1[Product],"Laptop") -> 5
M32: =SUMIFS(Table1[Revenue],Table1[Product],"Keyboard") -> 375 | N32: Keyboard
M33: =SUMIFS(Table1[Revenue],Table1[Product],"Monitor") -> 795 | N33: Monitor
M34: =SUMIFS(Table1[Revenue],Table1[Product],"Desk Chair") -> 400 | N34: Desk Chair
M35: =SUMIFS(Table1[Revenue],Table1[Product],"Standing Desk") -> 850 | N35: Standing Dest
M36: =SUMIFS(Table1[Revenue],Table1[Product],"Office Chair") -> 459 | N36: Office Chair

Sheet Product_Lookup
A1: Product | B1: Cost_Price | C1: Supplier
A2: Laptop | B2: 800 | C2: TechSupply Co
A3: Mouse | B3: 15 | C3: TechSupply Co
A4: Keyboard | B4: 45 | C4: TechSupply Co
A5: Monitor | B5: 200 | C5: DisplayPro Ltd
A6: Desk Chair | B6: 150 | C6: FurniCorp
A7: Standing Desk | B7: 350 | C7: FurniCorp
A8: Office Chair | B8: 120 | C8: FurniCorp

Sheet Target_Sales
D9: Region | E9: Monthly_Target
D10: Brisbane | E10: 10000
D11: Sydney | E11: 12000
D12: Melbourne | E12: 8000
D13: Perth | E13: 6000

Sheet Dashboard1
A1: "SALES ANALYSIS DASHBOARD"
A2: "January 2024"
A4: "KEY METRICS"
A5: "Total Revenue:" | B5: =SUM(Sales_Data!J:J) -> 8919.3182
A6: "Total Orders:" | B6: =COUNTA(Sales_Data!A11:A25) -> 15
A7: "Average Order Value:" | B7: =B5/B6 -> 594.62121
A8: "Total Profit:" | B8: =SUM(Sales_Data!M11:M25) -> 3021.5
A10: "TOP PERFORMERS"
A11: "Best Region:" | B11: =INDEX(Sales_Data!F:F,MATCH(MAX(Sales_Data!J:J),Sales_Data!J:J,0)) -> Brisbane
A12: "Best Product:" | B12: =INDEX(Table4[product],MATCH(MAX(Table4[helper_column]),Table4[helper_column],0)) -> Laptop
A13: "Highest Profit Margin:" | B13: =ROUND(MAX(Sales_Data!Q:Q),2)&"%" -> 652.39%
A15: "INSIGHTS"
A16: "Electronics Revenue %:" | B16: =Sales_Data!H4 -> 80.765876
A17: "Furniture Revenue %:" | B17: =Sales_Data!H5 -> 19.234124
A18: "Average Discount:" | B18: =ROUND(AVERAGE(Sales_Data!I:I)*100,2)&"%" -> 9.33%
